MANIFEST.in
README
setup.py
docs/.DS_Store
docs/Changelog.rst
docs/Makefile
docs/client.rst
docs/components.rst
docs/conf.py
docs/connectors.rst
docs/exceptions.rst
docs/index.rst
docs/listeners.rst
docs/strategies.rst
docs/_build/.DS_Store
docs/_build/doctrees/Changelog.doctree
docs/_build/doctrees/client.doctree
docs/_build/doctrees/components.doctree
docs/_build/doctrees/connectors.doctree
docs/_build/doctrees/environment.pickle
docs/_build/doctrees/exceptions.doctree
docs/_build/doctrees/index.doctree
docs/_build/doctrees/listeners.doctree
docs/_build/doctrees/strategies.doctree
docs/_build/html/.buildinfo
docs/_build/html/Changelog.html
docs/_build/html/client.html
docs/_build/html/components.html
docs/_build/html/connectors.html
docs/_build/html/exceptions.html
docs/_build/html/genindex.html
docs/_build/html/index.html
docs/_build/html/listeners.html
docs/_build/html/objects.inv
docs/_build/html/py-modindex.html
docs/_build/html/search.html
docs/_build/html/searchindex.js
docs/_build/html/strategies.html
docs/_build/html/_sources/Changelog.txt
docs/_build/html/_sources/client.txt
docs/_build/html/_sources/components.txt
docs/_build/html/_sources/connectors.txt
docs/_build/html/_sources/exceptions.txt
docs/_build/html/_sources/index.txt
docs/_build/html/_sources/listeners.txt
docs/_build/html/_sources/strategies.txt
docs/_build/html/_static/ajax-loader.gif
docs/_build/html/_static/basic.css
docs/_build/html/_static/comment-bright.png
docs/_build/html/_static/comment-close.png
docs/_build/html/_static/comment.png
docs/_build/html/_static/doctools.js
docs/_build/html/_static/down-pressed.png
docs/_build/html/_static/down.png
docs/_build/html/_static/file.png
docs/_build/html/_static/jquery-1.11.1.js
docs/_build/html/_static/jquery.js
docs/_build/html/_static/minus.png
docs/_build/html/_static/plus.png
docs/_build/html/_static/pygments.css
docs/_build/html/_static/searchtools.js
docs/_build/html/_static/underscore-1.3.1.js
docs/_build/html/_static/underscore.js
hermes_pg.egg-info/PKG-INFO
hermes_pg.egg-info/SOURCES.txt
hermes_pg.egg-info/dependency_links.txt
hermes_pg.egg-info/pbr.json
hermes_pg.egg-info/requires.txt
hermes_pg.egg-info/top_level.txt